[
    {
        "id":  "s1",
        "text":  "מי בנה את תיבת נוח?",
        "type":  "multiple",
        "options":  [
                        "משה",
                        "נוח",
                        "אברהם",
                        "יוסף"
                    ],
        "correct_answer":  [
                               "נוח"
                           ],
        "age_group":  "1-3",
        "subject":  "תנ\"ך"
    },
    {
        "id":  "s2",
        "text":  "כמה זה 6 ועוד 7?",
        "type":  "open",
        "options":  [

                    ],
        "correct_answer":  [
                               "13",
                               "שלוש עשרה"
                           ],
        "age_group":  "1-3",
        "subject":  "חשבון"
    },
    {
        "id":  "s3",
        "text":  "מהי עיר הבירה של ישראל?",
        "type":  "multiple",
        "options":  [
                        "תל אביב",
                        "ירושלים",
                        "חיפה",
                        "באר שבע"
                    ],
        "correct_answer":  [
                               "ירושלים"
                           ],
        "age_group":  "1-3",
        "subject":  "ידע כללי"
    },
    {
        "id":  "s4",
        "text":  "לאה קנתה 8 תפוחים ונתנה 3 לחבר. כמה תפוחים נשארו לה?",
        "type":  "open",
        "options":  [

                    ],
        "correct_answer":  [
                               "5",
                               "חמישה"
                           ],
        "age_group":  "1-3",
        "subject":  "חשבון"
    },
    {
        "id":  "s5",
        "text":  "מה כולל בעלי חיים שאוכלים בשר בלבד?",
        "type":  "multiple",
        "options":  [
                        "אוכלי עשב",
                        "טורפים",
                        "יונקים",
                        "זוחלים"
                    ],
        "correct_answer":  [
                               "טורפים"
                           ],
        "age_group":  "1-3",
        "subject":  "הסקת מסקנות"
    },
    {
        "id":  "s6",
        "text":  "מה הצורה הנכונה: \u0027הם ___ לבית הספר\u0027?",
        "type":  "multiple",
        "options":  [
                        "הלך",
                        "הלכה",
                        "הלכו",
                        "ילך"
                    ],
        "correct_answer":  [
                               "הלכו"
                           ],
        "age_group":  "1-3",
        "subject":  "לשון"
    },
    {
        "id":  "s7",
        "text":  "כמה שבטים היו לבני ישראל?",
        "type":  "open",
        "options":  [

                    ],
        "correct_answer":  [
                               "12",
                               "שנים עשר"
                           ],
        "age_group":  "4-6",
        "subject":  "תנ\"ך"
    },
    {
        "id":  "s8",
        "text":  "מה תוצאת: 144 חלקי 12?",
        "type":  "open",
        "options":  [

                    ],
        "correct_answer":  [
                               "12",
                               "שנים עשר"
                           ],
        "age_group":  "4-6",
        "subject":  "חשבון"
    },
    {
        "id":  "s9",
        "text":  "מה שם הים הגדול ביותר בעולם?",
        "type":  "multiple",
        "options":  [
                        "האוקיינוס האטלנטי",
                        "האוקיינוס השקט",
                        "האוקיינוס ההודי",
                        "הים התיכון"
                    ],
        "correct_answer":  [
                               "האוקיינוס השקט"
                           ],
        "age_group":  "4-6",
        "subject":  "ידע כללי"
    },
    {
        "id":  "s10",
        "text":  "אם כל ציפורים הן בעלות כנפיים, ועטלף הוא בעל כנפיים - האם עטלף הוא ציפור?",
        "type":  "multiple",
        "options":  [
                        "כן, כי יש לו כנפיים",
                        "לא, כי הוא יונק",
                        "אי אפשר לדעת",
                        "כן, כי הוא עף"
                    ],
        "correct_answer":  [
                               "לא, כי הוא יונק"
                           ],
        "age_group":  "4-6",
        "subject":  "הסקת מסקנות"
    },
    {
        "id":  "s11",
        "text":  "מהי שגיאת הכתיב בביטוי: \u0027הוא אמר שהוא ילך לבד\u0027?",
        "type":  "multiple",
        "options":  [
                        "אין שגיאה",
                        "שגיאה ב\u0027אמר\u0027",
                        "שגיאה ב\u0027ילך\u0027",
                        "שגיאה ב\u0027לבד\u0027"
                    ],
        "correct_answer":  [
                               "אין שגיאה"
                           ],
        "age_group":  "4-6",
        "subject":  "לשון"
    },
    {
        "id":  "s12",
        "text":  "מי כתב את ספר תהלים?",
        "type":  "multiple",
        "options":  [
                        "שלמה המלך",
                        "דוד המלך",
                        "משה רבנו",
                        "אברהם אבינו"
                    ],
        "correct_answer":  [
                               "דוד המלך"
                           ],
        "age_group":  "4-6",
        "subject":  "תנ\"ך"
    },
    {
        "id":  "s13",
        "text":  "כמה זה 15 כפול 15?",
        "type":  "open",
        "options":  [

                    ],
        "correct_answer":  [
                               "225",
                               "מאתיים עשרים וחמש"
                           ],
        "age_group":  "4-6",
        "subject":  "חשבון"
    },
    {
        "id":  "s14",
        "text":  "באיזו יבשת נמצאת ישראל?",
        "type":  "multiple",
        "options":  [
                        "אפריקה",
                        "אירופה",
                        "אסיה",
                        "אמריקה"
                    ],
        "correct_answer":  [
                               "אסיה"
                           ],
        "age_group":  "1-3",
        "subject":  "ידע כללי"
    },
    {
        "id":  "s15",
        "text":  "אם גשם יורד רק כשיש עננים - ובחוץ יורד גשם - מה נוכל להסיק?",
        "type":  "open",
        "options":  [

                    ],
        "correct_answer":  [
                               "יש עננים",
                               "עננים בשמיים",
                               "מעונן"
                           ],
        "age_group":  "4-6",
        "subject":  "הסקת מסקנות"
    },
    {
        "id":  "s16",
        "text":  "באילו פרשות כתובות עשרת הדברות?",
        "type":  "multiple",
        "options":  [
                        "ויקהל, ואתחנן",
                        "יתרו, כי תשא",
                        "יתרו, בהעלותך",
                        "יתרו, ואתחנן"
                    ],
        "correct_answer":  [
                               "יתרו, ואתחנן"
                           ],
        "age_group":  "4-6",
        "subject":  "תנ\"ך"
    },
    {
        "id":  "s17",
        "text":  "איפה כתוב בתורה \"חמרים חמרים\"?",
        "type":  "multiple",
        "options":  [
                        "בעניין דור הפלגה",
                        "בעבודת פרך במצרים",
                        "במכת צפרדע",
                        "במלאכת המשכן"
                    ],
        "correct_answer":  [
                               "בעניין דור הפלגה"
                           ],
        "age_group":  "4-6",
        "subject":  "תנ\"ך"
    },
    {
        "id":  "s18",
        "text":  "איזה מקום נקרא \"מחניים\"?",
        "type":  "multiple",
        "options":  [
                        "מקום מפגש יעקב ועשיו",
                        "מקום מפגש יעקב ולבן",
                        "מקום מפגש יעקב והמלאך",
                        "מקום מפגש יעקב ויוסף"
                    ],
        "correct_answer":  [
                               "מקום מפגש יעקב והמלאך"
                           ],
        "age_group":  "4-6",
        "subject":  "תנ\"ך"
    },
    {
        "id":  "s19",
        "text":  "איך קראו לבית אל במקור?",
        "type":  "multiple",
        "options":  [
                        "לוז",
                        "אפרת",
                        "בית לחם",
                        "אלון בכות"
                    ],
        "correct_answer":  [
                               "לוז"
                           ],
        "age_group":  "4-6",
        "subject":  "תנ\"ך"
    },
    {
        "id":  "s20",
        "text":  "באיזו פרשה כתובה מכת בכורות?",
        "type":  "multiple",
        "options":  [
                        "בשלח",
                        "שמות",
                        "וארא",
                        "בא"
                    ],
        "correct_answer":  [
                               "בא"
                           ],
        "age_group":  "4-6",
        "subject":  "תנ\"ך"
    },
    {
        "id":  "s21",
        "text":  "בכיתה ט2 יש 6 תלמידות שמרכיבות משקפיים. ידוע כי הן מהוות 12% מכלל התלמידות בכיתה. כמה תלמידות יש בכיתה ט2?",
        "type":  "multiple",
        "options":  [
                        "25",
                        "30",
                        "40",
                        "50"
                    ],
        "correct_answer":  [
                               "50"
                           ],
        "age_group":  "4-6",
        "subject":  "חשבון"
    },
    {
        "id":  "s22",
        "text":  "8 חולצות עולות 240 ש\"ח. מה יהיה המחיר של 20 חולצות?",
        "type":  "multiple",
        "options":  [
                        "600",
                        "300",
                        "400",
                        "800"
                    ],
        "correct_answer":  [
                               "600"
                           ],
        "age_group":  "4-6",
        "subject":  "חשבון"
    },
    {
        "id":  "s23",
        "text":  "לאחותי נולד בן כשהייתה בת 31 ונולדה לה בת כשהייתה בת 34. בת כמה אחותי היום, אם סכום הגילאים של שלושתם הוא 52?",
        "type":  "multiple",
        "options":  [
                        "37",
                        "35",
                        "38",
                        "39"
                    ],
        "correct_answer":  [
                               "39"
                           ],
        "age_group":  "4-6",
        "subject":  "חשבון"
    },
    {
        "id":  "s24",
        "text":  "יוסף ואליעזר עבדו יום אחד וקיבלו יחד 1000 ש\"ח. יוסף עבד פי 3 מאליעזר. כמה קיבל יוסף?",
        "type":  "multiple",
        "options":  [
                        "250",
                        "750",
                        "850",
                        "350"
                    ],
        "correct_answer":  [
                               "750"
                           ],
        "age_group":  "4-6",
        "subject":  "חשבון"
    },
    {
        "id":  "s25",
        "text":  "לבית דפוס יש עבודת הדפסה של 54,000 עותקים. מכונת דפוס אחת מדפיסה 30 עותקים בארבע דקות. בכמה מכונות יש להשתמש כדי לסיים את העבודה ב-6 שעות?",
        "type":  "multiple",
        "options":  [
                        "20",
                        "40",
                        "35",
                        "28"
                    ],
        "correct_answer":  [
                               "20"
                           ],
        "age_group":  "4-6",
        "subject":  "חשבון"
    },
    {
        "id":  "s26",
        "text":  "סוחר קנה תיק ב-20 ש\"ח ומכר ב-25 ש\"ח. כמה ירוויח על סחורה של תיקים שעלתה 700 ש\"ח?",
        "type":  "multiple",
        "options":  [
                        "190",
                        "215",
                        "105",
                        "175"
                    ],
        "correct_answer":  [
                               "175"
                           ],
        "age_group":  "4-6",
        "subject":  "חשבון"
    },
    {
        "id":  "s27",
        "text":  "סכום גילן של ארבע בנות דודות הוא 65. מה היה סכום הגילאים שלהן לפני חמש שנים?",
        "type":  "multiple",
        "options":  [
                        "45",
                        "60",
                        "33",
                        "52"
                    ],
        "correct_answer":  [
                               "45"
                           ],
        "age_group":  "4-6",
        "subject":  "חשבון"
    },
    {
        "id":  "s28",
        "text":  "רק צבים לא ממהרים. איזו מסקנה נכונה?",
        "type":  "multiple",
        "options":  [
                        "רק לא צבים ממהרים",
                        "אם לא צב אז לא ממהר",
                        "אם לא צב אז ממהר",
                        "אם אינך ממהר אתה לא צב"
                    ],
        "correct_answer":  [
                               "אם לא צב אז ממהר"
                           ],
        "age_group":  "4-6",
        "subject":  "הסקת מסקנות"
    },
    {
        "id":  "s29",
        "text":  "רק מי שנובח נושך. איזו מסקנה נכונה?",
        "type":  "multiple",
        "options":  [
                        "כל מי שנובח נושך",
                        "כלב שלא נובח אינו נושך",
                        "אם לא נושך אז לא נובח",
                        "רק מי שלא נובח לא נושך"
                    ],
        "correct_answer":  [
                               "כלב שלא נובח אינו נושך"
                           ],
        "age_group":  "4-6",
        "subject":  "הסקת מסקנות"
    },
    {
        "id":  "s30",
        "text":  "אם אתה צעיר אז אתה חסר מנוח. איזו מסקנה נכונה?",
        "type":  "multiple",
        "options":  [
                        "כל חסרי המנוחה הם צעירים",
                        "רק מי שאינו חסר מנוח הוא זקן",
                        "רק חסרי מנוח צעירים",
                        "אם אתה זקן אז אתה נינוח"
                    ],
        "correct_answer":  [
                               "רק חסרי מנוח צעירים"
                           ],
        "age_group":  "4-6",
        "subject":  "הסקת מסקנות"
    },
    {
        "id":  "s31",
        "text":  "כל הרוסים אוהבים לישון. איזו מסקנה נכונה?",
        "type":  "multiple",
        "options":  [
                        "רק מי שאוהב לישון הוא רוסי",
                        "אם אתה רוסי אז אתה בהכרח אוהב לישון",
                        "רק מי שלא רוסי לא אוהב לישון",
                        "מי שלא אוהב לישון יכול להיות רוסי"
                    ],
        "correct_answer":  [
                               "אם אתה רוסי אז אתה בהכרח אוהב לישון"
                           ],
        "age_group":  "4-6",
        "subject":  "הסקת מסקנות"
    },
    {
        "id":  "s32",
        "text":  "לא רק תוכים עצלנים. איזו מסקנה הכי מתאימה?",
        "type":  "multiple",
        "options":  [
                        "גם אנשים יכולים להיות עצלנים",
                        "רק אם אתה תוכי אתה עצלן",
                        "מי שלא תוכי יכול להיות לא עצלן"
                    ],
        "correct_answer":  [
                               "גם אנשים יכולים להיות עצלנים"
                           ],
        "age_group":  "4-6",
        "subject":  "הסקת מסקנות"
    },
    {
        "id":  "s33",
        "text":  "המילה \"שרעף\" היא:",
        "type":  "multiple",
        "options":  [
                        "מחשבה",
                        "שרפרף",
                        "סוג של אגוז",
                        "מתקן להנחת רעפים"
                    ],
        "correct_answer":  [
                               "מחשבה"
                           ],
        "age_group":  "4-6",
        "subject":  "לשון"
    },
    {
        "id":  "s34",
        "text":  "פירוש המילה \"נאלם\" הוא:",
        "type":  "multiple",
        "options":  [
                        "הרעיש",
                        "לחש",
                        "השתתק",
                        "נהיה אילם"
                    ],
        "correct_answer":  [
                               "השתתק"
                           ],
        "age_group":  "4-6",
        "subject":  "לשון"
    },
    {
        "id":  "s35",
        "text":  "\"לגדוד\" הוא שם פעולת הקטיף של:",
        "type":  "multiple",
        "options":  [
                        "תמרים",
                        "תאנים",
                        "זיתים",
                        "תפוזים"
                    ],
        "correct_answer":  [
                               "תמרים"
                           ],
        "age_group":  "4-6",
        "subject":  "לשון"
    },
    {
        "id":  "s36",
        "text":  "המילה \"ליש\" פירושה:",
        "type":  "multiple",
        "options":  [
                        "לישה של בצק",
                        "קציר",
                        "אריה",
                        "מערוך"
                    ],
        "correct_answer":  [
                               "אריה"
                           ],
        "age_group":  "4-6",
        "subject":  "לשון"
    },
    {
        "id":  "s37",
        "text":  "נאקה היא:",
        "type":  "multiple",
        "options":  [
                        "לביאה",
                        "נקבת החמור",
                        "סוסה",
                        "נקבת הגמל"
                    ],
        "correct_answer":  [
                               "נקבת הגמל"
                           ],
        "age_group":  "4-6",
        "subject":  "לשון"
    },
    {
        "id":  "s38",
        "text":  "ההפך מחם פירושו:",
        "type":  "multiple",
        "options":  [
                        "פושר",
                        "חמים",
                        "צונן",
                        "קפוא"
                    ],
        "correct_answer":  [
                               "צונן"
                           ],
        "age_group":  "4-6",
        "subject":  "לשון"
    },
    {
        "id":  "s39",
        "text":  "\"כוסיה\" היא:",
        "type":  "multiple",
        "options":  [
                        "כיסוי לספה",
                        "כפפה",
                        "גרב ארוך",
                        "ציפית לכרית"
                    ],
        "correct_answer":  [
                               "גרב ארוך"
                           ],
        "age_group":  "4-6",
        "subject":  "לשון"
    },
    {
        "id":  "s40",
        "text":  "איזה תחום חוקר הזואולוג?",
        "type":  "multiple",
        "options":  [
                        "עולם החי",
                        "עולם הצומח",
                        "הרכב הגזים באטמוספירה"
                    ],
        "correct_answer":  [
                               "עולם החי"
                           ],
        "age_group":  "4-6",
        "subject":  "ידע כללי"
    },
    {
        "id":  "s41",
        "text":  "פלס מים בנוי על פי:",
        "type":  "multiple",
        "options":  [
                        "כוח המשיכה",
                        "חוק כלים שלובים",
                        "מחזור המים בטבע"
                    ],
        "correct_answer":  [
                               "כוח המשיכה"
                           ],
        "age_group":  "4-6",
        "subject":  "ידע כללי"
    },
    {
        "id":  "s42",
        "text":  "מאוויים הם:",
        "type":  "multiple",
        "options":  [
                        "תשוקות",
                        "שבחים",
                        "כאבים"
                    ],
        "correct_answer":  [
                               "תשוקות"
                           ],
        "age_group":  "4-6",
        "subject":  "ידע כללי"
    },
    {
        "id":  "s43",
        "text":  "מעגל חשמלי פתוח פירושו:",
        "type":  "multiple",
        "options":  [
                        "מקור להתחשמלות",
                        "עיגול פתוח שמדליק אור",
                        "2 התשובות נכונות"
                    ],
        "correct_answer":  [
                               "2 התשובות נכונות"
                           ],
        "age_group":  "4-6",
        "subject":  "ידע כללי"
    },
    {
        "id":  "s44",
        "text":  "משמעות המילה אספקלריה היא:",
        "type":  "multiple",
        "options":  [
                        "מחלת עור",
                        "מראה",
                        "מפתן הדלת"
                    ],
        "correct_answer":  [
                               "מראה"
                           ],
        "age_group":  "4-6",
        "subject":  "ידע כללי"
    },
    {
        "id":  "s45",
        "text":  "אק\"ג פירושו:",
        "type":  "multiple",
        "options":  [
                        "מחלת לב",
                        "תרשים של הלב",
                        "פעילות המוח"
                    ],
        "correct_answer":  [
                               "תרשים של הלב"
                           ],
        "age_group":  "4-6",
        "subject":  "ידע כללי"
    },
    {
        "id":  "s46",
        "text":  "ישראל חתמה הסכם שלום בפעם הראשונה עם:",
        "type":  "multiple",
        "options":  [
                        "סוריה",
                        "ירדן",
                        "לבנון",
                        "מצרים"
                    ],
        "correct_answer":  [
                               "מצרים"
                           ],
        "age_group":  "4-6",
        "subject":  "ידע כללי"
    },
    {
        "id":  "s47",
        "text":  "הלבלב הוא איבר שמפריש את ההורמון:",
        "type":  "multiple",
        "options":  [
                        "סרוטונין",
                        "אינסולין",
                        "אדרנלין",
                        "דופמין"
                    ],
        "correct_answer":  [
                               "אינסולין"
                           ],
        "age_group":  "4-6",
        "subject":  "ידע כללי"
    },
    {
        "id":  "s48",
        "text":  "פוטוסינתזה היא:",
        "type":  "multiple",
        "options":  [
                        "עיצוב תמונה בפוטושופ",
                        "תהליך המרת אנרגיית אור לאנרגיה כימית",
                        "צילום של חומרים סינתטיים"
                    ],
        "correct_answer":  [
                               "תהליך המרת אנרגיית אור לאנרגיה כימית"
                           ],
        "age_group":  "4-6",
        "subject":  "ידע כללי"
    },
    {
        "id":  "s49",
        "text":  "מלקוש הוא:",
        "type":  "multiple",
        "options":  [
                        "הגשם האחרון שיורד בשנה",
                        "מלקות שמקבלים כתחליף למעצר",
                        "כלי קדום לניכוש עשבים באדמה"
                    ],
        "correct_answer":  [
                               "הגשם האחרון שיורד בשנה"
                           ],
        "age_group":  "4-6",
        "subject":  "ידע כללי"
    }
]
